{
  "runtime": "Net70",
  "defaultVariables": null,
  "documentGenerator": {
    "fromDocument": {
      "json": "{\r\n  \"openapi\": \"3.0.1\",\r\n  \"info\": {\r\n    \"title\": \"Backend\",\r\n    \"version\": \"1.0\"\r\n  },\r\n  \"paths\": {\r\n    \"/Auth/Login\": {\r\n      \"post\": {\r\n        \"tags\": [\r\n          \"Auth\"\r\n        ],\r\n        \"requestBody\": {\r\n          \"content\": {\r\n            \"application/json\": {\r\n              \"schema\": {\r\n                \"$ref\": \"#/components/schemas/LoginBody\"\r\n              }\r\n            },\r\n            \"text/json\": {\r\n              \"schema\": {\r\n                \"$ref\": \"#/components/schemas/LoginBody\"\r\n              }\r\n            },\r\n            \"application/*+json\": {\r\n              \"schema\": {\r\n                \"$ref\": \"#/components/schemas/LoginBody\"\r\n              }\r\n            }\r\n          }\r\n        },\r\n        \"responses\": {\r\n          \"200\": {\r\n            \"description\": \"Success\",\r\n            \"content\": {\r\n              \"text/plain\": {\r\n                \"schema\": {\r\n                  \"$ref\": \"#/components/schemas/LoginResponse\"\r\n                }\r\n              },\r\n              \"application/json\": {\r\n                \"schema\": {\r\n                  \"$ref\": \"#/components/schemas/LoginResponse\"\r\n                }\r\n              },\r\n              \"text/json\": {\r\n                \"schema\": {\r\n                  \"$ref\": \"#/components/schemas/LoginResponse\"\r\n                }\r\n              }\r\n            }\r\n          }\r\n        }\r\n      }\r\n    },\r\n    \"/Auth/Register\": {\r\n      \"post\": {\r\n        \"tags\": [\r\n          \"Auth\"\r\n        ],\r\n        \"requestBody\": {\r\n          \"content\": {\r\n            \"application/json\": {\r\n              \"schema\": {\r\n                \"$ref\": \"#/components/schemas/LoginBody\"\r\n              }\r\n            },\r\n            \"text/json\": {\r\n              \"schema\": {\r\n                \"$ref\": \"#/components/schemas/LoginBody\"\r\n              }\r\n            },\r\n            \"application/*+json\": {\r\n              \"schema\": {\r\n                \"$ref\": \"#/components/schemas/LoginBody\"\r\n              }\r\n            }\r\n          }\r\n        },\r\n        \"responses\": {\r\n          \"200\": {\r\n            \"description\": \"Success\",\r\n            \"content\": {\r\n              \"text/plain\": {\r\n                \"schema\": {\r\n                  \"$ref\": \"#/components/schemas/UserModel\"\r\n                }\r\n              },\r\n              \"application/json\": {\r\n                \"schema\": {\r\n                  \"$ref\": \"#/components/schemas/UserModel\"\r\n                }\r\n              },\r\n              \"text/json\": {\r\n                \"schema\": {\r\n                  \"$ref\": \"#/components/schemas/UserModel\"\r\n                }\r\n              }\r\n            }\r\n          }\r\n        }\r\n      }\r\n    },\r\n    \"/Auth/VerifyToken\": {\r\n      \"get\": {\r\n        \"tags\": [\r\n          \"Auth\"\r\n        ],\r\n        \"parameters\": [\r\n          {\r\n            \"name\": \"token\",\r\n            \"in\": \"query\",\r\n            \"schema\": {\r\n              \"type\": \"string\"\r\n            }\r\n          }\r\n        ],\r\n        \"responses\": {\r\n          \"200\": {\r\n            \"description\": \"Success\",\r\n            \"content\": {\r\n              \"text/plain\": {\r\n                \"schema\": {\r\n                  \"$ref\": \"#/components/schemas/JwtModel\"\r\n                }\r\n              },\r\n              \"application/json\": {\r\n                \"schema\": {\r\n                  \"$ref\": \"#/components/schemas/JwtModel\"\r\n                }\r\n              },\r\n              \"text/json\": {\r\n                \"schema\": {\r\n                  \"$ref\": \"#/components/schemas/JwtModel\"\r\n                }\r\n              }\r\n            }\r\n          }\r\n        }\r\n      }\r\n    },\r\n    \"/Content/Content\": {\r\n      \"get\": {\r\n        \"tags\": [\r\n          \"Content\"\r\n        ],\r\n        \"parameters\": [\r\n          {\r\n            \"name\": \"id\",\r\n            \"in\": \"query\",\r\n            \"schema\": {\r\n              \"type\": \"string\"\r\n            }\r\n          }\r\n        ],\r\n        \"responses\": {\r\n          \"200\": {\r\n            \"description\": \"Success\",\r\n            \"content\": {\r\n              \"text/plain\": {\r\n                \"schema\": {\r\n                  \"$ref\": \"#/components/schemas/ContentModel\"\r\n                }\r\n              },\r\n              \"application/json\": {\r\n                \"schema\": {\r\n                  \"$ref\": \"#/components/schemas/ContentModel\"\r\n                }\r\n              },\r\n              \"text/json\": {\r\n                \"schema\": {\r\n                  \"$ref\": \"#/components/schemas/ContentModel\"\r\n                }\r\n              }\r\n            }\r\n          }\r\n        }\r\n      },\r\n      \"post\": {\r\n        \"tags\": [\r\n          \"Content\"\r\n        ],\r\n        \"requestBody\": {\r\n          \"content\": {\r\n            \"application/json\": {\r\n              \"schema\": {\r\n                \"$ref\": \"#/components/schemas/ContentModel\"\r\n              }\r\n            },\r\n            \"text/json\": {\r\n              \"schema\": {\r\n                \"$ref\": \"#/components/schemas/ContentModel\"\r\n              }\r\n            },\r\n            \"application/*+json\": {\r\n              \"schema\": {\r\n                \"$ref\": \"#/components/schemas/ContentModel\"\r\n              }\r\n            }\r\n          }\r\n        },\r\n        \"responses\": {\r\n          \"200\": {\r\n            \"description\": \"Success\",\r\n            \"content\": {\r\n              \"text/plain\": {\r\n                \"schema\": {\r\n                  \"$ref\": \"#/components/schemas/ContentModel\"\r\n                }\r\n              },\r\n              \"application/json\": {\r\n                \"schema\": {\r\n                  \"$ref\": \"#/components/schemas/ContentModel\"\r\n                }\r\n              },\r\n              \"text/json\": {\r\n                \"schema\": {\r\n                  \"$ref\": \"#/components/schemas/ContentModel\"\r\n                }\r\n              }\r\n            }\r\n          }\r\n        }\r\n      },\r\n      \"put\": {\r\n        \"tags\": [\r\n          \"Content\"\r\n        ],\r\n        \"requestBody\": {\r\n          \"content\": {\r\n            \"application/json\": {\r\n              \"schema\": {\r\n                \"$ref\": \"#/components/schemas/ContentModel\"\r\n              }\r\n            },\r\n            \"text/json\": {\r\n              \"schema\": {\r\n                \"$ref\": \"#/components/schemas/ContentModel\"\r\n              }\r\n            },\r\n            \"application/*+json\": {\r\n              \"schema\": {\r\n                \"$ref\": \"#/components/schemas/ContentModel\"\r\n              }\r\n            }\r\n          }\r\n        },\r\n        \"responses\": {\r\n          \"200\": {\r\n            \"description\": \"Success\",\r\n            \"content\": {\r\n              \"text/plain\": {\r\n                \"schema\": {\r\n                  \"$ref\": \"#/components/schemas/ContentModel\"\r\n                }\r\n              },\r\n              \"application/json\": {\r\n                \"schema\": {\r\n                  \"$ref\": \"#/components/schemas/ContentModel\"\r\n                }\r\n              },\r\n              \"text/json\": {\r\n                \"schema\": {\r\n                  \"$ref\": \"#/components/schemas/ContentModel\"\r\n                }\r\n              }\r\n            }\r\n          }\r\n        }\r\n      },\r\n      \"delete\": {\r\n        \"tags\": [\r\n          \"Content\"\r\n        ],\r\n        \"parameters\": [\r\n          {\r\n            \"name\": \"id\",\r\n            \"in\": \"query\",\r\n            \"schema\": {\r\n              \"type\": \"string\"\r\n            }\r\n          }\r\n        ],\r\n        \"responses\": {\r\n          \"200\": {\r\n            \"description\": \"Success\",\r\n            \"content\": {\r\n              \"text/plain\": {\r\n                \"schema\": {\r\n                  \"$ref\": \"#/components/schemas/ContentModel\"\r\n                }\r\n              },\r\n              \"application/json\": {\r\n                \"schema\": {\r\n                  \"$ref\": \"#/components/schemas/ContentModel\"\r\n                }\r\n              },\r\n              \"text/json\": {\r\n                \"schema\": {\r\n                  \"$ref\": \"#/components/schemas/ContentModel\"\r\n                }\r\n              }\r\n            }\r\n          }\r\n        }\r\n      }\r\n    },\r\n    \"/Content/Contents\": {\r\n      \"get\": {\r\n        \"tags\": [\r\n          \"Content\"\r\n        ],\r\n        \"parameters\": [\r\n          {\r\n            \"name\": \"email\",\r\n            \"in\": \"query\",\r\n            \"schema\": {\r\n              \"type\": \"string\"\r\n            }\r\n          }\r\n        ],\r\n        \"responses\": {\r\n          \"200\": {\r\n            \"description\": \"Success\",\r\n            \"content\": {\r\n              \"text/plain\": {\r\n                \"schema\": {\r\n                  \"type\": \"array\",\r\n                  \"items\": {\r\n                    \"$ref\": \"#/components/schemas/ContentModel\"\r\n                  }\r\n                }\r\n              },\r\n              \"application/json\": {\r\n                \"schema\": {\r\n                  \"type\": \"array\",\r\n                  \"items\": {\r\n                    \"$ref\": \"#/components/schemas/ContentModel\"\r\n                  }\r\n                }\r\n              },\r\n              \"text/json\": {\r\n                \"schema\": {\r\n                  \"type\": \"array\",\r\n                  \"items\": {\r\n                    \"$ref\": \"#/components/schemas/ContentModel\"\r\n                  }\r\n                }\r\n              }\r\n            }\r\n          }\r\n        }\r\n      },\r\n      \"post\": {\r\n        \"tags\": [\r\n          \"Content\"\r\n        ],\r\n        \"requestBody\": {\r\n          \"content\": {\r\n            \"application/json\": {\r\n              \"schema\": {\r\n                \"type\": \"array\",\r\n                \"items\": {\r\n                  \"$ref\": \"#/components/schemas/ContentModel\"\r\n                }\r\n              }\r\n            },\r\n            \"text/json\": {\r\n              \"schema\": {\r\n                \"type\": \"array\",\r\n                \"items\": {\r\n                  \"$ref\": \"#/components/schemas/ContentModel\"\r\n                }\r\n              }\r\n            },\r\n            \"application/*+json\": {\r\n              \"schema\": {\r\n                \"type\": \"array\",\r\n                \"items\": {\r\n                  \"$ref\": \"#/components/schemas/ContentModel\"\r\n                }\r\n              }\r\n            }\r\n          }\r\n        },\r\n        \"responses\": {\r\n          \"200\": {\r\n            \"description\": \"Success\",\r\n            \"content\": {\r\n              \"text/plain\": {\r\n                \"schema\": {\r\n                  \"type\": \"array\",\r\n                  \"items\": {\r\n                    \"$ref\": \"#/components/schemas/ContentModel\"\r\n                  }\r\n                }\r\n              },\r\n              \"application/json\": {\r\n                \"schema\": {\r\n                  \"type\": \"array\",\r\n                  \"items\": {\r\n                    \"$ref\": \"#/components/schemas/ContentModel\"\r\n                  }\r\n                }\r\n              },\r\n              \"text/json\": {\r\n                \"schema\": {\r\n                  \"type\": \"array\",\r\n                  \"items\": {\r\n                    \"$ref\": \"#/components/schemas/ContentModel\"\r\n                  }\r\n                }\r\n              }\r\n            }\r\n          }\r\n        }\r\n      },\r\n      \"put\": {\r\n        \"tags\": [\r\n          \"Content\"\r\n        ],\r\n        \"requestBody\": {\r\n          \"content\": {\r\n            \"application/json\": {\r\n              \"schema\": {\r\n                \"type\": \"array\",\r\n                \"items\": {\r\n                  \"$ref\": \"#/components/schemas/ContentModel\"\r\n                }\r\n              }\r\n            },\r\n            \"text/json\": {\r\n              \"schema\": {\r\n                \"type\": \"array\",\r\n                \"items\": {\r\n                  \"$ref\": \"#/components/schemas/ContentModel\"\r\n                }\r\n              }\r\n            },\r\n            \"application/*+json\": {\r\n              \"schema\": {\r\n                \"type\": \"array\",\r\n                \"items\": {\r\n                  \"$ref\": \"#/components/schemas/ContentModel\"\r\n                }\r\n              }\r\n            }\r\n          }\r\n        },\r\n        \"responses\": {\r\n          \"200\": {\r\n            \"description\": \"Success\",\r\n            \"content\": {\r\n              \"text/plain\": {\r\n                \"schema\": {\r\n                  \"type\": \"array\",\r\n                  \"items\": {\r\n                    \"$ref\": \"#/components/schemas/ContentModel\"\r\n                  }\r\n                }\r\n              },\r\n              \"application/json\": {\r\n                \"schema\": {\r\n                  \"type\": \"array\",\r\n                  \"items\": {\r\n                    \"$ref\": \"#/components/schemas/ContentModel\"\r\n                  }\r\n                }\r\n              },\r\n              \"text/json\": {\r\n                \"schema\": {\r\n                  \"type\": \"array\",\r\n                  \"items\": {\r\n                    \"$ref\": \"#/components/schemas/ContentModel\"\r\n                  }\r\n                }\r\n              }\r\n            }\r\n          }\r\n        }\r\n      },\r\n      \"delete\": {\r\n        \"tags\": [\r\n          \"Content\"\r\n        ],\r\n        \"requestBody\": {\r\n          \"content\": {\r\n            \"application/json\": {\r\n              \"schema\": {\r\n                \"type\": \"array\",\r\n                \"items\": {\r\n                  \"type\": \"string\"\r\n                }\r\n              }\r\n            },\r\n            \"text/json\": {\r\n              \"schema\": {\r\n                \"type\": \"array\",\r\n                \"items\": {\r\n                  \"type\": \"string\"\r\n                }\r\n              }\r\n            },\r\n            \"application/*+json\": {\r\n              \"schema\": {\r\n                \"type\": \"array\",\r\n                \"items\": {\r\n                  \"type\": \"string\"\r\n                }\r\n              }\r\n            }\r\n          }\r\n        },\r\n        \"responses\": {\r\n          \"200\": {\r\n            \"description\": \"Success\",\r\n            \"content\": {\r\n              \"text/plain\": {\r\n                \"schema\": {\r\n                  \"type\": \"array\",\r\n                  \"items\": {\r\n                    \"$ref\": \"#/components/schemas/ContentModel\"\r\n                  }\r\n                }\r\n              },\r\n              \"application/json\": {\r\n                \"schema\": {\r\n                  \"type\": \"array\",\r\n                  \"items\": {\r\n                    \"$ref\": \"#/components/schemas/ContentModel\"\r\n                  }\r\n                }\r\n              },\r\n              \"text/json\": {\r\n                \"schema\": {\r\n                  \"type\": \"array\",\r\n                  \"items\": {\r\n                    \"$ref\": \"#/components/schemas/ContentModel\"\r\n                  }\r\n                }\r\n              }\r\n            }\r\n          }\r\n        }\r\n      }\r\n    },\r\n    \"/Email/Registration\": {\r\n      \"post\": {\r\n        \"tags\": [\r\n          \"Email\"\r\n        ],\r\n        \"requestBody\": {\r\n          \"content\": {\r\n            \"application/json\": {\r\n              \"schema\": {\r\n                \"$ref\": \"#/components/schemas/UserModel\"\r\n              }\r\n            },\r\n            \"text/json\": {\r\n              \"schema\": {\r\n                \"$ref\": \"#/components/schemas/UserModel\"\r\n              }\r\n            },\r\n            \"application/*+json\": {\r\n              \"schema\": {\r\n                \"$ref\": \"#/components/schemas/UserModel\"\r\n              }\r\n            }\r\n          }\r\n        },\r\n        \"responses\": {\r\n          \"200\": {\r\n            \"description\": \"Success\",\r\n            \"content\": {\r\n              \"text/plain\": {\r\n                \"schema\": {\r\n                  \"$ref\": \"#/components/schemas/EmailResponse\"\r\n                }\r\n              },\r\n              \"application/json\": {\r\n                \"schema\": {\r\n                  \"$ref\": \"#/components/schemas/EmailResponse\"\r\n                }\r\n              },\r\n              \"text/json\": {\r\n                \"schema\": {\r\n                  \"$ref\": \"#/components/schemas/EmailResponse\"\r\n                }\r\n              }\r\n            }\r\n          }\r\n        }\r\n      }\r\n    },\r\n    \"/Email/ResetPassword\": {\r\n      \"post\": {\r\n        \"tags\": [\r\n          \"Email\"\r\n        ],\r\n        \"requestBody\": {\r\n          \"content\": {\r\n            \"application/json\": {\r\n              \"schema\": {\r\n                \"$ref\": \"#/components/schemas/UserModel\"\r\n              }\r\n            },\r\n            \"text/json\": {\r\n              \"schema\": {\r\n                \"$ref\": \"#/components/schemas/UserModel\"\r\n              }\r\n            },\r\n            \"application/*+json\": {\r\n              \"schema\": {\r\n                \"$ref\": \"#/components/schemas/UserModel\"\r\n              }\r\n            }\r\n          }\r\n        },\r\n        \"responses\": {\r\n          \"200\": {\r\n            \"description\": \"Success\",\r\n            \"content\": {\r\n              \"text/plain\": {\r\n                \"schema\": {\r\n                  \"$ref\": \"#/components/schemas/EmailResponse\"\r\n                }\r\n              },\r\n              \"application/json\": {\r\n                \"schema\": {\r\n                  \"$ref\": \"#/components/schemas/EmailResponse\"\r\n                }\r\n              },\r\n              \"text/json\": {\r\n                \"schema\": {\r\n                  \"$ref\": \"#/components/schemas/EmailResponse\"\r\n                }\r\n              }\r\n            }\r\n          }\r\n        }\r\n      }\r\n    },\r\n    \"/User/User\": {\r\n      \"get\": {\r\n        \"tags\": [\r\n          \"User\"\r\n        ],\r\n        \"parameters\": [\r\n          {\r\n            \"name\": \"email\",\r\n            \"in\": \"query\",\r\n            \"schema\": {\r\n              \"type\": \"string\"\r\n            }\r\n          }\r\n        ],\r\n        \"responses\": {\r\n          \"200\": {\r\n            \"description\": \"Success\",\r\n            \"content\": {\r\n              \"text/plain\": {\r\n                \"schema\": {\r\n                  \"$ref\": \"#/components/schemas/UserModel\"\r\n                }\r\n              },\r\n              \"application/json\": {\r\n                \"schema\": {\r\n                  \"$ref\": \"#/components/schemas/UserModel\"\r\n                }\r\n              },\r\n              \"text/json\": {\r\n                \"schema\": {\r\n                  \"$ref\": \"#/components/schemas/UserModel\"\r\n                }\r\n              }\r\n            }\r\n          }\r\n        }\r\n      },\r\n      \"post\": {\r\n        \"tags\": [\r\n          \"User\"\r\n        ],\r\n        \"requestBody\": {\r\n          \"content\": {\r\n            \"application/json\": {\r\n              \"schema\": {\r\n                \"$ref\": \"#/components/schemas/UserModel\"\r\n              }\r\n            },\r\n            \"text/json\": {\r\n              \"schema\": {\r\n                \"$ref\": \"#/components/schemas/UserModel\"\r\n              }\r\n            },\r\n            \"application/*+json\": {\r\n              \"schema\": {\r\n                \"$ref\": \"#/components/schemas/UserModel\"\r\n              }\r\n            }\r\n          }\r\n        },\r\n        \"responses\": {\r\n          \"200\": {\r\n            \"description\": \"Success\",\r\n            \"content\": {\r\n              \"text/plain\": {\r\n                \"schema\": {\r\n                  \"$ref\": \"#/components/schemas/UserModel\"\r\n                }\r\n              },\r\n              \"application/json\": {\r\n                \"schema\": {\r\n                  \"$ref\": \"#/components/schemas/UserModel\"\r\n                }\r\n              },\r\n              \"text/json\": {\r\n                \"schema\": {\r\n                  \"$ref\": \"#/components/schemas/UserModel\"\r\n                }\r\n              }\r\n            }\r\n          }\r\n        }\r\n      },\r\n      \"put\": {\r\n        \"tags\": [\r\n          \"User\"\r\n        ],\r\n        \"requestBody\": {\r\n          \"content\": {\r\n            \"application/json\": {\r\n              \"schema\": {\r\n                \"$ref\": \"#/components/schemas/UserModel\"\r\n              }\r\n            },\r\n            \"text/json\": {\r\n              \"schema\": {\r\n                \"$ref\": \"#/components/schemas/UserModel\"\r\n              }\r\n            },\r\n            \"application/*+json\": {\r\n              \"schema\": {\r\n                \"$ref\": \"#/components/schemas/UserModel\"\r\n              }\r\n            }\r\n          }\r\n        },\r\n        \"responses\": {\r\n          \"200\": {\r\n            \"description\": \"Success\",\r\n            \"content\": {\r\n              \"text/plain\": {\r\n                \"schema\": {\r\n                  \"$ref\": \"#/components/schemas/UserModel\"\r\n                }\r\n              },\r\n              \"application/json\": {\r\n                \"schema\": {\r\n                  \"$ref\": \"#/components/schemas/UserModel\"\r\n                }\r\n              },\r\n              \"text/json\": {\r\n                \"schema\": {\r\n                  \"$ref\": \"#/components/schemas/UserModel\"\r\n                }\r\n              }\r\n            }\r\n          }\r\n        }\r\n      },\r\n      \"delete\": {\r\n        \"tags\": [\r\n          \"User\"\r\n        ],\r\n        \"parameters\": [\r\n          {\r\n            \"name\": \"email\",\r\n            \"in\": \"query\",\r\n            \"schema\": {\r\n              \"type\": \"string\"\r\n            }\r\n          }\r\n        ],\r\n        \"responses\": {\r\n          \"200\": {\r\n            \"description\": \"Success\",\r\n            \"content\": {\r\n              \"text/plain\": {\r\n                \"schema\": {\r\n                  \"$ref\": \"#/components/schemas/UserModel\"\r\n                }\r\n              },\r\n              \"application/json\": {\r\n                \"schema\": {\r\n                  \"$ref\": \"#/components/schemas/UserModel\"\r\n                }\r\n              },\r\n              \"text/json\": {\r\n                \"schema\": {\r\n                  \"$ref\": \"#/components/schemas/UserModel\"\r\n                }\r\n              }\r\n            }\r\n          }\r\n        }\r\n      }\r\n    },\r\n    \"/User/Users\": {\r\n      \"get\": {\r\n        \"tags\": [\r\n          \"User\"\r\n        ],\r\n        \"parameters\": [\r\n          {\r\n            \"name\": \"firstName\",\r\n            \"in\": \"query\",\r\n            \"schema\": {\r\n              \"type\": \"string\"\r\n            }\r\n          },\r\n          {\r\n            \"name\": \"lastName\",\r\n            \"in\": \"query\",\r\n            \"schema\": {\r\n              \"type\": \"string\"\r\n            }\r\n          },\r\n          {\r\n            \"name\": \"birthdate\",\r\n            \"in\": \"query\",\r\n            \"schema\": {\r\n              \"type\": \"string\"\r\n            }\r\n          }\r\n        ],\r\n        \"responses\": {\r\n          \"200\": {\r\n            \"description\": \"Success\",\r\n            \"content\": {\r\n              \"text/plain\": {\r\n                \"schema\": {\r\n                  \"type\": \"array\",\r\n                  \"items\": {\r\n                    \"$ref\": \"#/components/schemas/UserModel\"\r\n                  }\r\n                }\r\n              },\r\n              \"application/json\": {\r\n                \"schema\": {\r\n                  \"type\": \"array\",\r\n                  \"items\": {\r\n                    \"$ref\": \"#/components/schemas/UserModel\"\r\n                  }\r\n                }\r\n              },\r\n              \"text/json\": {\r\n                \"schema\": {\r\n                  \"type\": \"array\",\r\n                  \"items\": {\r\n                    \"$ref\": \"#/components/schemas/UserModel\"\r\n                  }\r\n                }\r\n              }\r\n            }\r\n          }\r\n        }\r\n      },\r\n      \"post\": {\r\n        \"tags\": [\r\n          \"User\"\r\n        ],\r\n        \"requestBody\": {\r\n          \"content\": {\r\n            \"application/json\": {\r\n              \"schema\": {\r\n                \"type\": \"array\",\r\n                \"items\": {\r\n                  \"$ref\": \"#/components/schemas/UserModel\"\r\n                }\r\n              }\r\n            },\r\n            \"text/json\": {\r\n              \"schema\": {\r\n                \"type\": \"array\",\r\n                \"items\": {\r\n                  \"$ref\": \"#/components/schemas/UserModel\"\r\n                }\r\n              }\r\n            },\r\n            \"application/*+json\": {\r\n              \"schema\": {\r\n                \"type\": \"array\",\r\n                \"items\": {\r\n                  \"$ref\": \"#/components/schemas/UserModel\"\r\n                }\r\n              }\r\n            }\r\n          }\r\n        },\r\n        \"responses\": {\r\n          \"200\": {\r\n            \"description\": \"Success\",\r\n            \"content\": {\r\n              \"text/plain\": {\r\n                \"schema\": {\r\n                  \"type\": \"array\",\r\n                  \"items\": {\r\n                    \"$ref\": \"#/components/schemas/UserModel\"\r\n                  }\r\n                }\r\n              },\r\n              \"application/json\": {\r\n                \"schema\": {\r\n                  \"type\": \"array\",\r\n                  \"items\": {\r\n                    \"$ref\": \"#/components/schemas/UserModel\"\r\n                  }\r\n                }\r\n              },\r\n              \"text/json\": {\r\n                \"schema\": {\r\n                  \"type\": \"array\",\r\n                  \"items\": {\r\n                    \"$ref\": \"#/components/schemas/UserModel\"\r\n                  }\r\n                }\r\n              }\r\n            }\r\n          }\r\n        }\r\n      },\r\n      \"put\": {\r\n        \"tags\": [\r\n          \"User\"\r\n        ],\r\n        \"requestBody\": {\r\n          \"content\": {\r\n            \"application/json\": {\r\n              \"schema\": {\r\n                \"type\": \"array\",\r\n                \"items\": {\r\n                  \"$ref\": \"#/components/schemas/UserModel\"\r\n                }\r\n              }\r\n            },\r\n            \"text/json\": {\r\n              \"schema\": {\r\n                \"type\": \"array\",\r\n                \"items\": {\r\n                  \"$ref\": \"#/components/schemas/UserModel\"\r\n                }\r\n              }\r\n            },\r\n            \"application/*+json\": {\r\n              \"schema\": {\r\n                \"type\": \"array\",\r\n                \"items\": {\r\n                  \"$ref\": \"#/components/schemas/UserModel\"\r\n                }\r\n              }\r\n            }\r\n          }\r\n        },\r\n        \"responses\": {\r\n          \"200\": {\r\n            \"description\": \"Success\",\r\n            \"content\": {\r\n              \"text/plain\": {\r\n                \"schema\": {\r\n                  \"type\": \"array\",\r\n                  \"items\": {\r\n                    \"$ref\": \"#/components/schemas/UserModel\"\r\n                  }\r\n                }\r\n              },\r\n              \"application/json\": {\r\n                \"schema\": {\r\n                  \"type\": \"array\",\r\n                  \"items\": {\r\n                    \"$ref\": \"#/components/schemas/UserModel\"\r\n                  }\r\n                }\r\n              },\r\n              \"text/json\": {\r\n                \"schema\": {\r\n                  \"type\": \"array\",\r\n                  \"items\": {\r\n                    \"$ref\": \"#/components/schemas/UserModel\"\r\n                  }\r\n                }\r\n              }\r\n            }\r\n          }\r\n        }\r\n      }\r\n    }\r\n  },\r\n  \"components\": {\r\n    \"schemas\": {\r\n      \"ContentModel\": {\r\n        \"required\": [\r\n          \"email\"\r\n        ],\r\n        \"type\": \"object\",\r\n        \"properties\": {\r\n          \"id\": {\r\n            \"type\": \"string\",\r\n            \"nullable\": true\r\n          },\r\n          \"dateCreated\": {\r\n            \"type\": \"string\",\r\n            \"format\": \"date-time\",\r\n            \"nullable\": true\r\n          },\r\n          \"dateUpdated\": {\r\n            \"type\": \"string\",\r\n            \"format\": \"date-time\",\r\n            \"nullable\": true\r\n          },\r\n          \"caption\": {\r\n            \"type\": \"string\",\r\n            \"nullable\": true\r\n          },\r\n          \"likes\": {\r\n            \"type\": \"integer\",\r\n            \"format\": \"int32\"\r\n          },\r\n          \"mediaType\": {\r\n            \"$ref\": \"#/components/schemas/MediaType\"\r\n          },\r\n          \"email\": {\r\n            \"minLength\": 1,\r\n            \"type\": \"string\",\r\n            \"format\": \"email\"\r\n          },\r\n          \"mediaUrl\": {\r\n            \"type\": \"string\",\r\n            \"nullable\": true\r\n          }\r\n        },\r\n        \"additionalProperties\": false\r\n      },\r\n      \"EmailResponse\": {\r\n        \"type\": \"object\",\r\n        \"properties\": {\r\n          \"sent\": {\r\n            \"type\": \"boolean\",\r\n            \"nullable\": true\r\n          }\r\n        },\r\n        \"additionalProperties\": false\r\n      },\r\n      \"JwtModel\": {\r\n        \"type\": \"object\",\r\n        \"properties\": {\r\n          \"email\": {\r\n            \"type\": \"string\",\r\n            \"nullable\": true\r\n          },\r\n          \"fullName\": {\r\n            \"type\": \"string\",\r\n            \"nullable\": true\r\n          },\r\n          \"birthDate\": {\r\n            \"type\": \"string\",\r\n            \"nullable\": true\r\n          }\r\n        },\r\n        \"additionalProperties\": false\r\n      },\r\n      \"LoginBody\": {\r\n        \"type\": \"object\",\r\n        \"properties\": {\r\n          \"email\": {\r\n            \"type\": \"string\",\r\n            \"nullable\": true\r\n          },\r\n          \"password\": {\r\n            \"type\": \"string\",\r\n            \"nullable\": true\r\n          }\r\n        },\r\n        \"additionalProperties\": false\r\n      },\r\n      \"LoginResponse\": {\r\n        \"type\": \"object\",\r\n        \"properties\": {\r\n          \"token\": {\r\n            \"type\": \"string\",\r\n            \"nullable\": true\r\n          }\r\n        },\r\n        \"additionalProperties\": false\r\n      },\r\n      \"MediaType\": {\r\n        \"enum\": [\r\n          0,\r\n          1,\r\n          2,\r\n          3\r\n        ],\r\n        \"type\": \"integer\",\r\n        \"format\": \"int32\"\r\n      },\r\n      \"UserModel\": {\r\n        \"required\": [\r\n          \"email\"\r\n        ],\r\n        \"type\": \"object\",\r\n        \"properties\": {\r\n          \"id\": {\r\n            \"type\": \"string\",\r\n            \"nullable\": true\r\n          },\r\n          \"password\": {\r\n            \"type\": \"string\",\r\n            \"nullable\": true\r\n          },\r\n          \"firstName\": {\r\n            \"type\": \"string\",\r\n            \"nullable\": true\r\n          },\r\n          \"lastName\": {\r\n            \"type\": \"string\",\r\n            \"nullable\": true\r\n          },\r\n          \"birthDate\": {\r\n            \"type\": \"string\",\r\n            \"nullable\": true\r\n          },\r\n          \"email\": {\r\n            \"minLength\": 1,\r\n            \"type\": \"string\",\r\n            \"format\": \"email\"\r\n          },\r\n          \"following\": {\r\n            \"type\": \"array\",\r\n            \"items\": {\r\n              \"type\": \"string\"\r\n            },\r\n            \"nullable\": true\r\n          },\r\n          \"followers\": {\r\n            \"type\": \"array\",\r\n            \"items\": {\r\n              \"type\": \"string\"\r\n            },\r\n            \"nullable\": true\r\n          },\r\n          \"profilePictureUrl\": {\r\n            \"type\": \"string\",\r\n            \"nullable\": true\r\n          },\r\n          \"photosUrl\": {\r\n            \"type\": \"string\",\r\n            \"nullable\": true\r\n          },\r\n          \"reelsUrl\": {\r\n            \"type\": \"string\",\r\n            \"nullable\": true\r\n          }\r\n        },\r\n        \"additionalProperties\": false\r\n      }\r\n    }\r\n  }\r\n}",
      "url": "http://redocly.github.io/redoc/openapi.yaml",
      "output": null,
      "newLineBehavior": "Auto"
    }
  },
  "codeGenerators": {
    "openApiToTypeScriptClient": {
      "className": "{controller}Client",
      "moduleName": "",
      "namespace": "",
      "typeScriptVersion": 4.3,
      "template": "Axios",
      "promiseType": "Promise",
      "httpClass": "HttpClient",
      "withCredentials": false,
      "useSingletonProvider": false,
      "injectionTokenType": "OpaqueToken",
      "rxJsVersion": 6.0,
      "dateTimeType": "Date",
      "nullValue": "Undefined",
      "generateClientClasses": true,
      "generateClientInterfaces": false,
      "generateOptionalParameters": true,
      "exportTypes": true,
      "wrapDtoExceptions": false,
      "exceptionClass": "ApiException",
      "clientBaseClass": "AuthorizedApiBase",
      "wrapResponses": false,
      "wrapResponseMethods": [],
      "generateResponseClasses": true,
      "responseClass": "SwaggerResponse",
      "protectedMethods": [],
      "configurationClass": "",
      "useTransformOptionsMethod": true,
      "useTransformResultMethod": false,
      "generateDtoTypes": true,
      "operationGenerationMode": "MultipleClientsFromOperationId",
      "markOptionalProperties": true,
      "generateCloneMethod": false,
      "typeStyle": "Interface",
      "enumStyle": "Enum",
      "useLeafType": false,
      "classTypes": [],
      "extendedClasses": [],
      "extensionCode": null,
      "generateDefaultValues": true,
      "excludedTypeNames": [],
      "excludedParameterNames": [],
      "handleReferences": false,
      "generateTypeCheckFunctions": false,
      "generateConstructorInterface": true,
      "convertConstructorInterfaceData": false,
      "importRequiredTypes": true,
      "useGetBaseUrlMethod": false,
      "baseUrlTokenName": "API_BASE_URL",
      "queryNullValue": "",
      "useAbortSignal": false,
      "inlineNamedDictionaries": false,
      "inlineNamedAny": false,
      "includeHttpContext": false,
      "templateDirectory": null,
      "typeNameGeneratorType": null,
      "propertyNameGeneratorType": null,
      "enumNameGeneratorType": null,
      "serviceHost": null,
      "serviceSchemes": null,
      "output": "../frontend/main/src/api/Client.ts",
      "newLineBehavior": "Auto"
    }
  }
}